navis_fastcore-0.1.0.dist-info/METADATA
navis_fastcore-0.1.0.dist-info/WHEEL
navis_fastcore-0.1.0.dist-info/licenses/LICENSE
navis_fastcore/__init__.py
navis_fastcore/__version__.py
navis_fastcore/_fastcore.cpython-314t-darwin.so
navis_fastcore/dag.py
navis_fastcore/nblast.py
navis_fastcore/wrappers/__init__.py
navis_fastcore/wrappers/csgraph.py
navis_fastcore-0.1.0.dist-info/RECORD
