Metadata-Version: 2.4
Name: navis-fastcore
Version: 0.1.0
Classifier: Development Status :: 2 - Pre-Alpha
Classifier: Intended Audience :: Developers
Classifier: License :: OSI Approved :: MIT License
Classifier: Natural Language :: English
Classifier: Programming Language :: Rust
Classifier: Programming Language :: Python :: 3
Classifier: Programming Language :: Python :: 3.9
Classifier: Programming Language :: Python :: 3.10
Classifier: Programming Language :: Python :: 3.11
Classifier: Programming Language :: Python :: 3.12
Classifier: Programming Language :: Python :: 3.13
Classifier: Programming Language :: Python :: Free Threading :: 2 - Beta
Requires-Dist: numpy>=1.21.0
License-File: LICENSE
Summary: NAVis core functions reimplemented in Rust.
Author-email: Philipp Schlegel <pms70@cam.ac.uk>
Requires-Python: >=3.9
Project-URL: Documentation, https://schlegelp.github.io/fastcore-rs/
Project-URL: Repository, https://github.com/schlegelp/fastcore-rs
Project-URL: Issues, https://github.com/schlegelp/fastcore-rs/issues
Project-URL: Changelog, https://github.com/schlegelp/fastcore-rs/blob/master/CHANGELOG.md
